pyw/__init__.py
pyw/config/__init__.py
pyw_config-0.0.0.post2.dist-info/METADATA
pyw_config-0.0.0.post2.dist-info/WHEEL
pyw_config-0.0.0.post2.dist-info/licenses/LICENSE
pyw_config-0.0.0.post2.dist-info/RECORD
