Metadata-Version: 2.4
Name: pyw-config
Version: 0.0.0.post2
Summary: Reserved placeholder for pyw-config (configuration utilities for pythonWoods suite)
Project-URL: Homepage, https://github.com/pythonWoods/pyw-config
Project-URL: Documentation, https://pythonwoods.dev/docs/pyw-config/latest/
Project-URL: Issues, https://github.com/pythonWoods/pyw-config/issues
Project-URL: Changelog, https://github.com/pythonWoods/pyw-config/releases
Author-email: pythonWoods <you@example.com>
License: MIT
License-File: LICENSE
Classifier: Development Status :: 2 - Pre-Alpha
Classifier: License :: OSI Approved :: MIT License
Classifier: Programming Language :: Python :: 3 :: Only
Classifier: Programming Language :: Python :: 3.11
Classifier: Typing :: Typed
Requires-Python: >=3.9
Requires-Dist: pyw-core>=0.0.0
